django_fake_database_backends/__init__.py
django_fake_database_backends/backends/__init__.py
django_fake_database_backends/backends/utils.py
django_fake_database_backends/backends/mysql/__init__.py
django_fake_database_backends/backends/mysql/base.py
django_fake_database_backends/backends/mysql/client.py
django_fake_database_backends/backends/mysql/creation.py
django_fake_database_backends/backends/mysql/fake_db.py
django_fake_database_backends/backends/mysql/features.py
django_fake_database_backends/backends/mysql/introspection.py
django_fake_database_backends/backends/mysql/operations.py
django_fake_database_backends/backends/mysql/schema.py
django_fake_database_backends/backends/mysql/validation.py
django_fake_database_backends/backends/postgresql/__init__.py
django_fake_database_backends/backends/postgresql/base.py
django_fake_database_backends/backends/postgresql/client.py
django_fake_database_backends/backends/postgresql/creation.py
django_fake_database_backends/backends/postgresql/fake_db.py
django_fake_database_backends/backends/postgresql/features.py
django_fake_database_backends/backends/postgresql/introspection.py
django_fake_database_backends/backends/postgresql/operations.py
django_fake_database_backends/backends/postgresql/schema.py
django_fake_database_backends/backends/postgresql/utils.py
django_fake_database_backends/backends/sqlite3/__init__.py
django_fake_database_backends/backends/sqlite3/base.py
django_fake_database_backends/backends/sqlite3/client.py
django_fake_database_backends/backends/sqlite3/creation.py
django_fake_database_backends/backends/sqlite3/fake_db.py
django_fake_database_backends/backends/sqlite3/features.py
django_fake_database_backends/backends/sqlite3/introspection.py
django_fake_database_backends/backends/sqlite3/operations.py
django_fake_database_backends/backends/sqlite3/schema.py
django_fake_database_backends/common/__init__.py
django_fake_database_backends/common/connection.py
django_fake_database_backends-0.1.1.dist-info/METADATA
django_fake_database_backends-0.1.1.dist-info/RECORD
django_fake_database_backends-0.1.1.dist-info/WHEEL
django_fake_database_backends-0.1.1.dist-info/top_level.txt
