Metadata-Version: 2.1
Name: django-fake-database-backends
Version: 0.1.1
Summary: Fake django database backends to generate sql without a real database
Home-page: https://github.com/David-Wobrock/django-fake-database-backends
Author: David Wobrock
Author-email: david.wobrock@gmail.com
License: MIT
Keywords: django database backend sqlmigrate
Platform: UNKNOWN
Classifier: Development Status :: 4 - Beta
Classifier: Intended Audience :: Developers
Classifier: Environment :: Web Environment
Classifier: Topic :: Database
Classifier: Framework :: Django
Classifier: Framework :: Django :: 1.11
Classifier: Framework :: Django :: 2.0
Classifier: Programming Language :: Python
Classifier: Programming Language :: Python :: 2
Classifier: Programming Language :: Python :: 2.7
Classifier: Programming Language :: Python :: 3
Classifier: Programming Language :: Python :: 3.4
Classifier: Programming Language :: Python :: 3.5
Classifier: Programming Language :: Python :: 3.6
Provides-Extra: test
Requires-Dist: django (>=1.11)
Provides-Extra: test
Requires-Dist: pytest; extra == 'test'
Requires-Dist: tox; extra == 'test'
Requires-Dist: pillow; extra == 'test'
Requires-Dist: mysqlclient; extra == 'test'
Requires-Dist: psycopg2-binary; extra == 'test'
